Metadata-Version: 2.1
Name: domaintools_api_beta
Version: 2.0.0
Summary: DomainTools Official Python API
Author-email: DomainTools <integrations@domaintools.com>
License: The MIT License (MIT)
Project-URL: Homepage, https://github.com/domaintools/python_api
Keywords: Python,Python3
Classifier: Development Status :: 5 - Production/Stable
Classifier: Intended Audience :: Developers
Classifier: Natural Language :: English
Classifier: Environment :: Console
Classifier: License :: OSI Approved :: MIT License
Classifier: Programming Language :: Python
Classifier: Programming Language :: Python :: 3
Classifier: Programming Language :: Python :: 3 :: Only
Classifier: Programming Language :: Python :: 3.6
Classifier: Programming Language :: Python :: 3.7
Classifier: Programming Language :: Python :: 3.8
Classifier: Programming Language :: Python :: 3.9
Classifier: Programming Language :: Python :: 3.10
Classifier: Topic :: Software Development :: Libraries
Classifier: Topic :: Utilities
Requires-Python: >=3.6
License-File: LICENSE
Requires-Dist: httpx
Requires-Dist: dateparser
Requires-Dist: rich
Requires-Dist: typer
Provides-Extra: test
Requires-Dist: pytest ; extra == 'test'
Requires-Dist: mock ; extra == 'test'
